srim/__init__.py
srim/config.py
srim/input.py
srim/output.py
srim/plot.py
srim/srim.py
srim/core/__init__.py
srim/core/element.py
srim/core/elementdb.py
srim/core/ion.py
srim/core/layer.py
srim/core/material.py
srim/core/target.py
srim/core/units.py
srim/core/utils.py
srim/data/elements.json
srim/data/elements.toml
srim/data/elements.yaml
srimpy-0.6.3.dist-info/LICENSE
srimpy-0.6.3.dist-info/METADATA
srimpy-0.6.3.dist-info/WHEEL
srimpy-0.6.3.dist-info/top_level.txt
srimpy-0.6.3.dist-info/RECORD
